check_soa_serials/__init__.py
check_soa_serials/__main__.py
check_soa_serials-1.0.0.data/scripts/check_soa_serials
check_soa_serials-1.0.0.dist-info/licenses/LICENSE
check_soa_serials-1.0.0.dist-info/METADATA
check_soa_serials-1.0.0.dist-info/WHEEL
check_soa_serials-1.0.0.dist-info/top_level.txt
check_soa_serials-1.0.0.dist-info/RECORD
