Metadata-Version: 2.4
Name: check_soa_serials
Version: 1.0.0
Summary: check_soa_serials is an Icinga2/Nagios plugin which compares the SOA serial numbers for the same DNS zone(s) from two different servers to ensure they are in sync
Author: cspeterson
Author-email: 
Project-URL: Documentation, https://github.com/theias/check_soa_serials
Project-URL: Bug Tracker, https://github.com/theias/check_soa_serials/issues
Project-URL: Source, https://github.com/theias/check_soa_serials
Project-URL: url, https://github.com/theias/check_soa_serials
Classifier: Programming Language :: Python :: 3
Classifier: License :: OSI Approved :: MIT License
Classifier: Operating System :: OS Independent
Requires-Python: >=3.6
License-File: LICENSE
Requires-Dist: dnspython==2.2.1; python_version < "3.9"
Requires-Dist: dnspython<3.0.0,>=2.6.1; python_version >= "3.9"
Requires-Dist: nagiosplugin<2.0.0,>=1.3.3
Dynamic: license-file
